<?xml version="1.0" encoding="UTF-8"?>

<!--Copyright (c) 2012 by Subset Games. All rights reserved.-->
<img x="-40" y="-24" w="328" h="420" />
<offsets>
	<floor x="164" y="210" />
	<cloak x="-27" y="-23" />
</offsets>
<thrusters sync="true">
    <thruster x="30" y="392">mu_fed_tac</thruster>
    <thruster x="55" y="392">mu_fed_tac</thruster>
    <thruster x="256" y="392">mu_fed_tac</thruster>
    <thruster x="281" y="392">mu_fed_tac</thruster>
    <thruster x="149" y="399">mu_fed_tac3</thruster>
</thrusters>
<weaponMounts>
	<mount x="222" y="194" rotate="false" mirror="false" gib="-1" slide="right" />
	<mount x="106" y="194" rotate="false" mirror="true" gib="-1" slide="left" />
	<mount x="200" y="66" rotate="false" mirror="false" gib="-1" slide="right" />
	<mount x="128" y="66" rotate="false" mirror="true" gib="-1" slide="left" />
</weaponMounts>
<explosion />

