<?xml version="1.0" encoding="UTF-8"?>

<!--Copyright (c) 2012 by Subset Games. All rights reserved.-->
<img x="-46" y="-55" w="320" h="338" />
<offsets>
	<floor x="160" y="169" />
	<cloak x="160" y="169" />
</offsets>
<weaponMounts>
	<mount x="221" y="84" rotate="false" mirror="false" gib="-1" slide="right" />
	<mount x="83" y="84" rotate="false" mirror="true" gib="-1" slide="left" />
	<mount x="279" y="174" rotate="false" mirror="false" gib="-1" slide="right" />
	<mount x="25" y="174" rotate="false" mirror="true" gib="-1" slide="left" />
</weaponMounts>
<explosion />

