<?xml version="1.0" encoding="UTF-8"?>

<!--Copyright (c) 2012 by Subset Games. All rights reserved.-->
<img x="-75" y="-27" w="399" h="458" />
<offsets>
	<floor x="199" y="229" />
	<cloak x="-25" y="-25" />
</offsets>
<weaponMounts>
	<mount x="72" y="120" rotate="false" mirror="true" gib="-1" slide="up" />
	<mount x="254" y="33" rotate="false" mirror="false" gib="-1" slide="up" />
	<mount x="408" y="78" rotate="false" mirror="false" gib="-1" slide="up" />
	<mount x="323" y="27" rotate="false" mirror="true" gib="-1" slide="no" />
	<mount x="142" y="27" rotate="false" mirror="true" gib="-1" slide="no" />
	<mount x="290" y="27" rotate="false" mirror="false" gib="-1" slide="no" />
</weaponMounts>
<explosion />

